<?xml version="1.0" encoding="UTF-8"?>
<SavedGameObject>
    <GameObject instanceId="3">
        <Tag hash_id="791473260" srcString="Road_Line"/>
        <Component name="TransformComponent" hash_id="3882513520">
            <Position x="0" y="0" z="0"/>
            <Rotation_Q x="0.70710677" y="0" z="0" w="0.70710671"/>
            <Scale x="6" y="30" z="1"/>
        </Component>
        <Component name="GeometryComponent" hash_id="36578682">
            <GeometryDescs>
                <Element>
                    <geometryID hash_id="3536424569" srcString="plane"/>
                    <slotIndex value="0"/>
                    <subMeshIndex value="0"/>
                </Element>
            </GeometryDescs>
        </Component>
        <Component name="MaterialComponent" hash_id="1886146475">
            <MaterialDesc>
                <Element>
                    <isRawShader value="false"/>
                    <materialID hash_id="4041468971" srcString="line_asphalt"/>
                    <slotIndex value="0"/>
                </Element>
            </MaterialDesc>
        </Component>
        <Component name="Render3DComponent" hash_id="4070531333"/>
    </GameObject>
</SavedGameObject>
